codebasic/__init__.py
codebasic/__main__.py
codebasic/cli.py
codebasic/config.py
codebasic-1.0.0.dist-info/METADATA
codebasic-1.0.0.dist-info/WHEEL
codebasic-1.0.0.dist-info/entry_points.txt
codebasic-1.0.0.dist-info/top_level.txt
codebasic-1.0.0.dist-info/RECORD
